<?xml version="1.0"?>
<ArrayOfString xmlns:xsd="http://www.w3.org/2001/XMLSchema" xmlns:xsi="http://www.w3.org/2001/XMLSchema-instance">
  <string>Data Source=172.16.96.95;Initial Catalog=GSPDev;User ID=csharp;Password=csharp.123</string>
  <string>Data Source=.;Initial Catalog=EFDb;Integrated Security=SSPI</string>
  <string>Data Source=172.16.96.56;Initial Catalog=NERP_TEST;User ID=erp;Password=erp.123</string>
  <string>Data Source=172.16.96.55\sql2014;Initial Catalog=GSP_TEST;User ID=csharp;Password=csharp.123</string>
</ArrayOfString>